S570/CSD_CSV.py
S570/CSD_CSV_clean.py
S570/__init__.py
S570-1.1.dist-info/METADATA
S570-1.1.dist-info/WHEEL
S570-1.1.dist-info/top_level.txt
S570-1.1.dist-info/RECORD
