Metadata-Version: 2.1
Name: S570
Version: 1.1
Summary: GPL570 platform microarray analyse files
Home-page: UNKNOWN
Author: Tigran MKrtchyan
Author-email: tigran.mkrt.bibi@gmail.com
License: MIT
Platform: UNKNOWN
